beatrica/__init__.py
beatrica/beatrica.py
beatrica/prompts.py
beatrica-2025.5.71632.dist-info/licenses/LICENSE
tests/__init__.py
tests/test_beatrica.py
beatrica-2025.5.71632.dist-info/METADATA
beatrica-2025.5.71632.dist-info/WHEEL
beatrica-2025.5.71632.dist-info/entry_points.txt
beatrica-2025.5.71632.dist-info/top_level.txt
beatrica-2025.5.71632.dist-info/RECORD
