Metadata-Version: 2.4
Name: beatrica
Version: 2025.5.71632
Summary: Beatrica is a tool for code review automation using large language models.
Home-page: https://github.com/chigwell/beatrica
Author: Eugene Evstafev
Author-email: chigwel@gmail.com
Classifier: Development Status :: 3 - Alpha
Classifier: Intended Audience :: Developers
Classifier: Programming Language :: Python :: 3
Classifier: Operating System :: OS Independent
Requires-Python: >=3.6
License-File: LICENSE
Requires-Dist: rich==13.7.1
Requires-Dist: beatrica-git==0.1.1
Requires-Dist: beatrica-embedding==0.1.1
Requires-Dist: langchain-openai==0.1.2
Requires-Dist: langchain-mistralai==0.1.1
Requires-Dist: chromadb==0.3.29
Provides-Extra: dev
Requires-Dist: pytest; extra == "dev"
Requires-Dist: pytest-cov; extra == "dev"
Requires-Dist: pytest-mock; extra == "dev"
Requires-Dist: coverage; extra == "dev"
Requires-Dist: flake8; extra == "dev"
Requires-Dist: black; extra == "dev"
Requires-Dist: isort; extra == "dev"
Requires-Dist: mypy; extra == "dev"
Requires-Dist: pre-commit; extra == "dev"
Requires-Dist: twine; extra == "dev"
Requires-Dist: wheel; extra == "dev"
Dynamic: author
Dynamic: author-email
Dynamic: classifier
Dynamic: description
Dynamic: description-content-type
Dynamic: home-page
Dynamic: license-file
Dynamic: provides-extra
Dynamic: requires-dist
Dynamic: requires-python
Dynamic: summary
